interfaces/__init__.py
interfaces/interfaces.py
mindbox_test_lib-0.2.0.dist-info/licenses/LICENSE
shapes/__init__.py
shapes/circle.py
shapes/triangle.py
mindbox_test_lib-0.2.0.dist-info/METADATA
mindbox_test_lib-0.2.0.dist-info/WHEEL
mindbox_test_lib-0.2.0.dist-info/top_level.txt
mindbox_test_lib-0.2.0.dist-info/RECORD
